README
setup.cfg
setup.py
YAMLTrak.egg-info/PKG-INFO
YAMLTrak.egg-info/SOURCES.txt
YAMLTrak.egg-info/dependency_links.txt
YAMLTrak.egg-info/requires.txt
YAMLTrak.egg-info/top_level.txt
YAMLTrak.egg-info/zip-safe
scripts/yt
yamltrak/__init__.py
yamltrak/argparse.py
yamltrak/commands.py