Metadata-Version: 1.0
Name: YAMLTrak
Version: 0.6.3
Summary: YAMLTrak ('yt is on top of hg'), the issue tracker that uses mercurial as a database
Home-page: http://dvdev.org
Author: Douglas Mayle
Author-email: douglas.mayle.org
License: LGPLv3
Platform: UNKNOWN
Classifier: Development Status :: 4 - Beta
Classifier: Environment :: Console
Classifier: Intended Audience :: Developers
Classifier: License :: OSI Approved :: GNU Library or Lesser General Public License (LGPL)
Classifier: Operating System :: OS Independent
Classifier: Programming Language :: Python :: 2.5
Classifier: Topic :: Software Development :: Bug Tracking
